{
  "programmes": [
    {
      "id": "2789",
      "titre": "Développeur DevOps",
      "description": "Développez des applications et apprenez à les faire évoluer en continu dans un environnement agile grâce à la spécialisation DevOps.\n\nAu Programme:\nConception et développement d’applications sécurisées\nDéploiement d’une application\nCycle de vie d’une application pour maintenir la qualité et la performance\nMise en place de méthodes d’amélioration continue\nPratiques DevOps au sein d’une organisation agile",
      "duree": "4 mois",
      "competences": [
        "Administration système",
        "Expérience avec les outils DevOps"
      ]
    },
    {
      "id": "b870",
      "titre": "Data Analyst ",
      "description": "Introduction à la formation\n\nDurant les premières semaines, vous allez : \n\nDécouvrir les grandes lignes de votre futur métier\nExpérimenter la pédagogie active de Simplon\nAcquérir rapidement une vision claire des compétences à maîtriser\nComprendre les critères d’évaluation menant à la certification finale",
      "duree": "6 mois",
      "competences": [
        "Exploitation d’une base de données",
        "Développer un programme d’intelligence artificielle ",
        "Développer la gestion des données analytiques d’un projet d’application"
      ]
    },
    {
      "id": "b3d0",
      "titre": "Développement Mobile – Simplon",
      "description": "TEST",
      "duree": "3mois",
      "competences": "Java, React "
    }
  ]
}